edgex_access/__init__.py
edgex_access/edgex_access.py
edgex_access/edgex_base.py
edgex_access/edgex_exceptions.py
edgex_access/edgex_fs.py
edgex_access/edgex_goog.py
edgex_access/edgex_mem.py
edgex_access/edgex_meta.py
edgex_access/edgex_s3.py
edgex_access/version.py
edgex_access-0.0.14.data/scripts/sp3
edgex_access-0.0.14.dist-info/LICENSE
edgex_access-0.0.14.dist-info/METADATA
edgex_access-0.0.14.dist-info/WHEEL
edgex_access-0.0.14.dist-info/top_level.txt
edgex_access-0.0.14.dist-info/RECORD
