Metadata-Version: 2.1
Name: edgex-access
Version: 0.0.14
Summary: S3 protocol Data access to AWS S3
Home-page: http://www.github.com/nacharya/edgex_access
Author: Nabin Acharya
Author-email: nabin.acharya@gmail.com
License: MIT
Project-URL: Bug Reports, https://github.com/nacharya/edgex_access/issues
Project-URL: Source, https://github.com/nacharya/edgex_access/
Keywords: requests edgex_access s3 scaleout store distributed
Platform: UNKNOWN
Classifier: Development Status :: 4 - Beta
Classifier: Intended Audience :: Science/Research
Classifier: Intended Audience :: Developers
Classifier: License :: OSI Approved :: BSD License
Classifier: Programming Language :: Python :: 3.6
Classifier: Programming Language :: Python :: 3 :: Only
Requires-Python: >=3
Requires-Dist: urllib3
Requires-Dist: requests-aws4auth
Requires-Dist: aiobotocore
Requires-Dist: simplejson
Requires-Dist: lxml
Requires-Dist: asyncio
